datoviz/__init__.py
datoviz/_app.py
datoviz/_axes.py
datoviz/_constants.py
datoviz/_ctypes.py
datoviz/_event.py
datoviz/_figure.py
datoviz/_panel.py
datoviz/_props.py
datoviz/_texture.py
datoviz/download.py
datoviz/interact.py
datoviz/ipython.py
datoviz/libdatoviz.so
datoviz/libvulkan.so.1
datoviz/shape_collection.py
datoviz/utils.py
datoviz/visuals.py
datoviz/backends/__init__.py
datoviz/backends/pyqt6.py
datoviz-0.3.5.dist-info/METADATA
datoviz-0.3.5.dist-info/WHEEL
datoviz-0.3.5.dist-info/top_level.txt
datoviz-0.3.5.dist-info/RECORD
