Metadata-Version: 2.1
Name: datoviz
Version: 0.3.5
Summary: Datoviz: high-performance rendering for scientific data visualization
Author-email: Cyrille Rossant <cyrille.rossant@gmail.com>
License: MIT
Project-URL: Homepage, https://github.com/datoviz/datoviz
Project-URL: Documentation, https://github.com/datoviz/datoviz
Project-URL: Source, https://github.com/datoviz/datoviz
Keywords: visualization,scientific visualization,vulkan,gpu,datoviz
Classifier: Programming Language :: Python :: 3
Classifier: License :: OSI Approved :: MIT License
Classifier: Operating System :: OS Independent
Requires-Python: >=3.8
Requires-Dist: numpy
Requires-Dist: requests
Requires-Dist: platformdirs
